library2notion/Models/Book.py
library2notion/Models/BookCollection.py
library2notion/Models/BookEpub.py
library2notion/Models/BookPaper.py
library2notion/Models/BookPdf.py
library2notion/Models/NotionBookCollection.py
library2notion/NotionIntegration.py
library2notion/ProgressBar.py
library2notion/__init__.py
library2notion/__main__py
library2notion/library2notion.py
library2notion/pyshical_book_template.paper
library2notion-1.1.1.dist-info/LICENSE
library2notion-1.1.1.dist-info/METADATA
library2notion-1.1.1.dist-info/WHEEL
library2notion-1.1.1.dist-info/entry_points.txt
library2notion-1.1.1.dist-info/RECORD
