Metadata-Version: 2.1
Name: library2notion
Version: 1.1.1
Summary: 
Author: helguera
Author-email: javier@javierhelguera.com
Requires-Python: >=3.7,<4.0
Classifier: Programming Language :: Python :: 3
Classifier: Programming Language :: Python :: 3.7
Classifier: Programming Language :: Python :: 3.8
Classifier: Programming Language :: Python :: 3.9
Classifier: Programming Language :: Python :: 3.10
Classifier: Programming Language :: Python :: 3.11
Requires-Dist: argparse (>=1.4.0,<2.0.0)
Requires-Dist: epub-meta (>=0.0.7,<0.0.8)
Requires-Dist: notion-client (>=2.0.0,<3.0.0)
Requires-Dist: pypdf2 (>=2.11.2,<3.0.0)
